{"sprint":true,"texturePack":"Exhibition V2","cape":true,"watermarkStatus":"Watermark","itemcolr":[1,0,1],"flyKey":"X","speed":true,"material":"ForceField","particles":true,"thud":true,"particle":"XP","scaffKey":"R","trail":true,"kstrokes":true,"icongrad":true,"smallitem":"Default","watermarkText":"tenacity","SlowAnims":true,"flySpeed":0,"nuker":true,"shopbypass":true,"toxicText":"Tenacity owns you all","resp":true,"KAnimation":"Slow","killaura":true,"fly":true,"textgrad":true,"BoxColor":[1,0,1],"antiKB":true,"at":true,"avColor":[1,0,1],"av":true,"speedCC":5,"arraylistStatus":"Arraylist","nofall":true,"scaff":true,"capecolor":[1,0.5960784554481506,0.8627451062202454]} 
